cybsi/__init__.py
cybsi/__version__.py
cybsi/api/__init__.py
cybsi/api/api.py
cybsi/api/artifact/__init__.py
cybsi/api/artifact/api.py
cybsi/api/artifact/enums.py
cybsi/api/auth/__init__.py
cybsi/api/auth/api_key.py
cybsi/api/auth/token.py
cybsi/api/client.py
cybsi/api/client_config.py
cybsi/api/custom_list/__init__.py
cybsi/api/custom_list/api.py
cybsi/api/data_source/__init__.py
cybsi/api/data_source/api.py
cybsi/api/data_source/api_types.py
cybsi/api/data_source/enums.py
cybsi/api/dictionary/__init__.py
cybsi/api/dictionary/api.py
cybsi/api/enrichment/__init__.py
cybsi/api/enrichment/analyzers.py
cybsi/api/enrichment/api.py
cybsi/api/enrichment/config_rules.py
cybsi/api/enrichment/enums.py
cybsi/api/enrichment/external_dbs.py
cybsi/api/enrichment/task_queue.py
cybsi/api/enrichment/tasks.py
cybsi/api/enum.py
cybsi/api/error.py
cybsi/api/internal/__init__.py
cybsi/api/internal/base.py
cybsi/api/internal/connector.py
cybsi/api/internal/multipart.py
cybsi/api/internal/time.py
cybsi/api/license/__init__.py
cybsi/api/license/api.py
cybsi/api/license/enums.py
cybsi/api/observable/__init__.py
cybsi/api/observable/aggregate_section.py
cybsi/api/observable/annotations.py
cybsi/api/observable/api.py
cybsi/api/observable/entities_api.py
cybsi/api/observable/entity.py
cybsi/api/observable/enums.py
cybsi/api/observable/links.py
cybsi/api/observable/relationships.py
cybsi/api/observable/view.py
cybsi/api/observation/__init__.py
cybsi/api/observation/api.py
cybsi/api/observation/archive.py
cybsi/api/observation/dns_lookup.py
cybsi/api/observation/enums.py
cybsi/api/observation/generic.py
cybsi/api/observation/network_session.py
cybsi/api/observation/threat.py
cybsi/api/observation/view.py
cybsi/api/observation/whois_lookup.py
cybsi/api/pagination.py
cybsi/api/replist/__init__.py
cybsi/api/replist/api.py
cybsi/api/replist/enums.py
cybsi/api/report/__init__.py
cybsi/api/report/api.py
cybsi/api/search/__init__.py
cybsi/api/search/api.py
cybsi/api/search/entities.py
cybsi_sdk-2.14.3.dist-info/LICENSE
cybsi_sdk-2.14.3.dist-info/METADATA
cybsi_sdk-2.14.3.dist-info/WHEEL
cybsi_sdk-2.14.3.dist-info/RECORD
